{
  "monitoring_interval": 3600,
  "auto_update": true,
  "backup_changes": true,
  "notify_changes": true,
  "quality_threshold": 0.95,
  "document_health_check": true,
  "automation_health_check": true,
  "structure_validation": true,
  "content_validation": true,
  "link_validation": true,
  "exclude_patterns": [
    "*.tmp",
    "*.bak",
    ".git/*",
    "node_modules/*",
    "__pycache__/*"
  ],
  "critical_files": [
    "doc/00_项目概览与导航/文档导航与索引.md",
    "doc/00_项目概览与导航/项目完成最终确认报告-2025.md",
    "doc/00_项目概览与导航/多任务推进全面完成最终总结报告-2025.md",
    "scripts/run_all_automation.py",
    "scripts/smart_document_manager.py",
    "scripts/continuous_monitoring.py"
  ],
  "notification_settings": {
    "email_notifications": false,
    "slack_notifications": false,
    "log_level": "INFO"
  },
  "update_settings": {
    "auto_update_interval": 86400,
    "backup_before_update": true,
    "validate_after_update": true
  },
  "quality_settings": {
    "min_document_size": 100,
    "required_sections": [
      "概览",
      "目标",
      "内容",
      "总结"
    ],
    "check_links": true,
    "check_images": false
  }
}
